textualitty/__init__.py
textualitty/__main__.py
textualitty/app.py
textual.icns
textualitty-0.2.7.dist-info/entry_points.txt
textualitty-0.2.7.dist-info/WHEEL
textualitty-0.2.7.dist-info/METADATA
textualitty-0.2.7.dist-info/RECORD
