Metadata-Version: 2.1
Name: textualitty
Version: 0.2.7
Summary: 
Author: Felix Ingram
Author-email: f.ingram@gmail.com
Requires-Python: >=3.10,<4.0
Classifier: Programming Language :: Python :: 3
Classifier: Programming Language :: Python :: 3.10
Classifier: Programming Language :: Python :: 3.11
Requires-Dist: click (>=8.1.3,<9.0.0)
Requires-Dist: rich (>=12.6.0,<13.0.0)
Requires-Dist: tomlkit (>=0.11.6,<0.12.0)
